[
  {
    "name": "Комиссия",
    "values": [
      {
        "name": "За сделку",
        "value": "0.3 %"
      }
    ]
  },
  {
    "name": "Депозитарное обслуживание",
    "values": [
      {
        "name": "Если торгуете в течение месяца",
        "value": "200 руб/мес"
      },
      {
        "name": "Если не торгуете",
        "value": "Бесплатно"
      }
    ]
  },
  {
    "name": "ДРУГИХ КОМИССИЙ НЕ БУДЕТ",
    "values": [
      {
        "name": "Тарифные условия установлены в документах на открытие вашего брокерского счета.",
        "value": ""
      }
    ]
  }
]